piicli/__init__.py
piicli/main.py
piicli/utils.py
piicli-1.0.0.dist-info/LICENSE
piicli-1.0.0.dist-info/METADATA
piicli-1.0.0.dist-info/WHEEL
piicli-1.0.0.dist-info/entry_points.txt
piicli-1.0.0.dist-info/RECORD
